pie_extended/__init__.py
pie_extended/__main__.py
pie_extended/tagger.py
pie_extended/cli/__init__.py
pie_extended/cli/main.py
pie_extended/cli/sub.py
pie_extended/cli/utils.py
pie_extended/models/__init__.py
pie_extended/models/dum/__init__.py
pie_extended/models/dum/imports.py
pie_extended/models/fr/__init__.py
pie_extended/models/fr/excluders.py
pie_extended/models/fr/imports.py
pie_extended/models/fr/processor.py
pie_extended/models/fr/tokenizer.py
pie_extended/models/freem/__init__.py
pie_extended/models/freem/imports.py
pie_extended/models/fro/__init__.py
pie_extended/models/fro/classes.py
pie_extended/models/fro/get.py
pie_extended/models/fro/imports.py
pie_extended/models/fro/processor.py
pie_extended/models/fro/tokenizer.py
pie_extended/models/grc/__init__.py
pie_extended/models/grc/imports.py
pie_extended/models/grc/processor.py
pie_extended/models/grc/tokenizer.py
pie_extended/models/lasla/__init__.py
pie_extended/models/lasla/_params.py
pie_extended/models/lasla/classes.py
pie_extended/models/lasla/consts.py
pie_extended/models/lasla/get.py
pie_extended/models/lasla/imports.py
pie_extended/models/lasla/processor.py
pie_extended/models/lasla/tokenizer.py
pie_extended/models/occ_cont/__init__.py
pie_extended/models/occ_cont/imports.py
pie_extended/models/occ_cont/processor.py
pie_extended/models/occ_cont/tokenizer.py
pie_extended/pipeline/__init__.py
pie_extended/pipeline/disambiguators/__init__.py
pie_extended/pipeline/disambiguators/autocat.py
pie_extended/pipeline/disambiguators/proto.py
pie_extended/pipeline/formatters/__init__.py
pie_extended/pipeline/formatters/glue.py
pie_extended/pipeline/formatters/proto.py
pie_extended/pipeline/iterators/__init__.py
pie_extended/pipeline/iterators/proto.py
pie_extended/pipeline/postprocessor/__init__.py
pie_extended/pipeline/postprocessor/glue.py
pie_extended/pipeline/postprocessor/memory.py
pie_extended/pipeline/postprocessor/proto.py
pie_extended/pipeline/postprocessor/rulebased.py
pie_extended-0.1.3.dist-info/LICENSE
pie_extended-0.1.3.dist-info/METADATA
pie_extended-0.1.3.dist-info/WHEEL
pie_extended-0.1.3.dist-info/entry_points.txt
pie_extended-0.1.3.dist-info/top_level.txt
pie_extended-0.1.3.dist-info/RECORD
