Metadata-Version: 2.1
Name: pie-extended
Version: 0.1.3
Summary: Extension for nlp-pie package
Home-page: https://github.com/hipster-philology/nlp-pie-taggers
Author: Thibault Clérice
License: MIT
Platform: UNKNOWN
Classifier: License :: OSI Approved :: MIT License
Classifier: Programming Language :: Python
Classifier: Programming Language :: Python :: 3
Classifier: Programming Language :: Python :: 3.6
Classifier: Programming Language :: Python :: Implementation :: CPython
Classifier: Programming Language :: Python :: Implementation :: PyPy
Classifier: Topic :: Text Processing :: Linguistic
Requires-Python: >=3.8.0
License-File: LICENSE
Requires-Dist: PaPie (~=0.4.0)
Requires-Dist: autodisambiguator (<1.0.0,>=0.0.1)
Requires-Dist: click (<8.0,>=7.0)
Requires-Dist: colorama (>=0.4.4)
Requires-Dist: numpy (<1.24.0)
Requires-Dist: regex
Requires-Dist: requests (~=2.25.0)
Requires-Dist: unidecode (~=1.1.1)
